django_seriously/__init__.py
django_seriously/py.typed
django_seriously/settings.py
django_seriously/authtoken/__init__.py
django_seriously/authtoken/admin.py
django_seriously/authtoken/apps.py
django_seriously/authtoken/authentication.py
django_seriously/authtoken/forms.py
django_seriously/authtoken/models.py
django_seriously/authtoken/utils.py
django_seriously/authtoken/migrations/0001_initial.py
django_seriously/authtoken/migrations/0002_token_last_seen_at_alter_token_scopes.py
django_seriously/authtoken/migrations/__init__.py
django_seriously/minimaluser/__init__.py
django_seriously/minimaluser/admin.py
django_seriously/minimaluser/apps.py
django_seriously/minimaluser/models.py
django_seriously/utils/__init__.py
django_seriously/utils/admin.py
django_seriously/utils/fields.py
django_seriously/utils/forms.py
django_seriously/utils/models.py
django_seriously/utils/pydantic.py
django_seriously/utils/schema.py
django_seriously/utils/settings.py
django_seriously-0.4.3.dist-info/LICENSE
django_seriously-0.4.3.dist-info/METADATA
django_seriously-0.4.3.dist-info/WHEEL
django_seriously-0.4.3.dist-info/top_level.txt
django_seriously-0.4.3.dist-info/RECORD
