Metadata-Version: 2.1
Name: django-seriously
Version: 0.4.3
Summary: Opinionated collection of Django and DRF tools that came in handy time and again.
Home-page: https://github.com/tfranzel/django-seriously
Author: T. Franzel
Author-email: tfranzel@gmail.com
License: BSD
Project-URL: Source, https://github.com/tfranzel/django-seriously
Classifier: Development Status :: 4 - Beta
Classifier: Environment :: Web Environment
Classifier: Framework :: Django
Classifier: Framework :: Django :: 3.2
Classifier: Framework :: Django :: 4.0
Classifier: Intended Audience :: Developers
Classifier: License :: OSI Approved :: BSD License
Classifier: Operating System :: OS Independent
Classifier: Natural Language :: English
Classifier: Programming Language :: Python :: 3
Classifier: Programming Language :: Python :: 3.6
Classifier: Programming Language :: Python :: 3.7
Classifier: Programming Language :: Python :: 3.8
Classifier: Programming Language :: Python :: 3.9
Classifier: Programming Language :: Python :: 3.10
Classifier: Topic :: Internet :: WWW/HTTP
Requires-Python: >=3.6
License-File: LICENSE
Requires-Dist: Django >=3.2
Requires-Dist: djangorestframework >=3.12.0
Requires-Dist: typing-extensions >=3.10.0.2
Requires-Dist: pydantic <2.0,>=1.8.2
